LICENSE
README.md
setup.py
CVE_2023_27524.egg-info/PKG-INFO
CVE_2023_27524.egg-info/SOURCES.txt
CVE_2023_27524.egg-info/dependency_links.txt
CVE_2023_27524.egg-info/entry_points.txt
CVE_2023_27524.egg-info/requires.txt
CVE_2023_27524.egg-info/top_level.txt
cve202327524/main.py
cve202327524/includes/__init__.py
cve202327524/includes/bot.py
cve202327524/includes/filereader.py
cve202327524/includes/scan.py
cve202327524/includes/writefile.py
cve202327524/utils/__init__.py
cve202327524/utils/configure.py
cve202327524/utils/const.py
cve202327524/utils/helpers.py
cve202327524/utils/status.py